travelmanager/__init__.py
travelmanager/schemas.py
travelmanager/travelmanager_api.py
travelmanager/modules/__init__.py
travelmanager/modules/availability.py
travelmanager/modules/booking.py
travelmanager/modules/relation.py
travelmanager/modules/station.py
python_travelmanager-1.3.0.dist-info/METADATA
python_travelmanager-1.3.0.dist-info/WHEEL
python_travelmanager-1.3.0.dist-info/licenses/LICENSE
python_travelmanager-1.3.0.dist-info/RECORD
