Metadata-Version: 2.3
Name: python_travelmanager
Version: 1.3.0
Summary: Python TravelManager
Author-email: Johannes Eimer <johannes.eimer@jep-dev.com>
License-Expression: MIT
License-File: LICENSE
Keywords: Python,TravelManager
Requires-Python: >=3.9
Requires-Dist: requests==2.32.3
